sealdb.py
sealdb-0.1.1.dist-info/licenses/LICENSE
sealdb-0.1.1.dist-info/METADATA
sealdb-0.1.1.dist-info/WHEEL
sealdb-0.1.1.dist-info/top_level.txt
sealdb-0.1.1.dist-info/RECORD
