Metadata-Version: 2.4
Name: sealdb
Version: 0.1.1
Summary: Sealdb the easiest db for python
Home-page: 
Author: Abolfazl Pourisa
Author-email: abolfazl190912@gmail.com
Classifier: Programming Language :: Python :: 3
Classifier: License :: OSI Approved :: MIT License
Classifier: Operating System :: OS Independent
Requires-Python: >=3.8
License-File: LICENSE
Dynamic: author
Dynamic: author-email
Dynamic: classifier
Dynamic: description-content-type
Dynamic: license-file
Dynamic: requires-python
Dynamic: summary
